BlacklistReport/BlacklistEntry.py
BlacklistReport/BlacklistReport.py
BlacklistReport/IpEntryPool.py
BlacklistReport/__init__.py
BlacklistReport/__threat_data.py
BlacklistReport/schema/ReportSchema.py
BlacklistReport/schema/__init__.py
BlacklistReport-0.5.0.dist-info/LICENSE
BlacklistReport-0.5.0.dist-info/METADATA
BlacklistReport-0.5.0.dist-info/WHEEL
BlacklistReport-0.5.0.dist-info/top_level.txt
BlacklistReport-0.5.0.dist-info/RECORD
