Metadata-Version: 2.1
Name: BlacklistReport
Version: 0.5.0
Summary: Bad Reputation (Blacklisted IP) Incident Reporting.
Home-page: https://git.vcjames.io/soc/dailyblacklistreporting
Author: dzellmer
License: GPLv3
Platform: UNKNOWN
Classifier: Programming Language :: Python :: 3
Classifier: License :: OSI Approved :: GNU General Public License v3 (GPLv3)
Classifier: Operating System :: OS Independent
Requires-Python: >=3.6
License-File: LICENSE
Requires-Dist: attrs (==20.3.0)
Requires-Dist: certifi (==2020.12.5)
Requires-Dist: chardet (==4.0.0)
Requires-Dist: GuardiPy (>=0.4.0)
Requires-Dist: idna (==2.10)
Requires-Dist: inflect (==5.0.2)
Requires-Dist: jsonschema (==3.2.0)
Requires-Dist: pyrsistent (==0.17.3)
Requires-Dist: requests (==2.25.1)
Requires-Dist: six (==1.15.0)
Requires-Dist: urllib3 (==1.26.3)
Requires-Dist: setuptools (>=56.0.0)
Requires-Dist: greynoise (>=0.9.0)
